Workbook

Sheet Read Me
A1: Item | B1: Description
A2: What this workbook is
A3: One contract per workbook | B3: Produced by the contract review skill from the contract text and the Start2 standards workbook, then checked by a person. Counts and the to-confirm line update when you edit the Findings sheet.
A4: How to use it
A5: 1. Summary | B5: Read the role, the counts and the number of findings to confirm. Check the role guess first: if it is wrong, nothing else applies.
A6: 2. Findings | B6: Work down the list. It is sorted Critical to Low. Fix, negotiate or accept each item, and change Severity or Type if you disagree. Every Critical, High and client-clause finding must be confirmed by a person.
A7: 3. Coverage | B7: Use it to see which standard clauses are present, partial, deviant or missing. It is a view; issues are listed in Findings.
A8: 4. Checks | B8: The 12 execution checks. A failed check also appears in Findings.
A9: 5. Documents not supplied | B9: Every outside document the contract names (general conditions, bids, policies, codes, links) that was not supplied with it. Terms in these documents were not reviewed. Obtain them and re-run the review.
A10: Severity
A11: Critical | B11: Do not sign as it stands. Reject threshold met, hard stop, wrong entity, no liability cap, blank essential fields.
A12: High | B12: Fix, or have the full sign-off chain knowingly accept it, before signing. Material cash, liability, IP, data, forum or scope exposure.
A13: Medium | B13: Should be fixed. Negotiable. Raises dispute risk but not direct cash loss.
A14: Low | B14: Housekeeping, optional clauses, accepted client clauses.
A15: Subjective wording | B15: A finding whose quoted text lets the counterparty alone judge Start2's work, payment or people (for example 'acceptable to Canada', 'to the satisfaction of', 'in its sole discretion') is raised one severity level and marked Yes in the Subjective column.
A16: Sheet: Summary (Item / Value / Where)
A17: Contract | B17: Name or title of the contract being reviewed.
A18: Source file | B18: File name of the contract that was reviewed.
A19: Status | B19: Draft (unsigned) or Executed (signed). Executed contracts get remediation wording instead of sign/no-sign.
A20: Contract type | B20: Service, Funding, Vendor or Other. Funding agreements (grants, claims, audits) read the fee and cost clauses differently.
A21: Whose paper | B21: Start2 template unmodified, Start2 template modified, or client or third-party paper. Sets the review lead time: 3 business days for the unmodified template, otherwise 5.
A22: Standards version | B22: Version of the standards workbook the contract was checked against.
A23: Our entity | B23: The Start2 entity in this contract. Guessed from the entity list and the text when not obvious.
A24: Our role | B24: Provider, Buyer or Other. The standards cover provider-side contracts only. If the role is not Provider, standards coverage is not applied and the To confirm line says so.
A25: Role basis | B25: One sentence on why that role was chosen. Always filled when the role was guessed.
A26: Counterparty | B26: The other party.
A27: Critical / High / Medium / Low | B27: Formulas: number of Findings at each severity.
A28: To confirm | B28: Formula: the number of Critical and High findings. These are logged for a person to confirm; nothing else is recommended.
... A32: Key facts (Fact / Value / Where) | B32: Facts used in the review: parties, dates, amounts, law, forum, language, annexes, with arithmetic checks. Where gives the contract reference and page.
A33: Sheet: Findings (one row per issue)
A34: # | B34: Running number.
A35: Severity | B35: Critical, High, Medium or Low (drop-down).
A36: Type | B36: Missing, Partial or Deviant (a standard clause); Client: Reject, Escalate, Conditional or Accept (a client-added clause matched to the playbook); Unclassified clause (not in the standard or playbook, generic screen); Commercial (fee, dates, arithmetic); Execution (a failed check); Not supplied (a document that forms part of the contract was not supplied, so its terms were not reviewed); Other.
A37: Clause | B37: Standard clause ID (for example LOL), the playbook row name, or Check n.
A38: Where | B38: Contract clause number and page, for example 13.1 (p. 10). 'Not in contract' for an absent clause.
A39: Quote | B39: Verbatim text from the contract: the full sentence or sub-clause, with the words the finding turns on in bold. '...' marks text left out between excerpts. Scanned contracts are transcribed from page images, so check the page before relying on a quote.
A40: Issue | B40: What the clause says in plain words, what it means for Start2 in practice, how it compares with the Start2 standard, and why it has this severity.
A41: Action | B41: What to do next and who does it: what to check internally, what to ask the counterparty for, and a fallback if they decline.
A42: Suggested language | B42: Wording to propose to the counterparty. For a standard clause, the Start2 standard language with the parties named as in this contract; otherwise wording written for this finding. Fill bracketed items and adjust before sending.
A43: Subjective | B43: Yes when the quoted text lets the counterparty alone judge Start2's work, payment or people. The severity already includes the one-level raise.
A44: Sheet: Coverage (one row per standard clause)
A45: ID | B45: Stable clause key from the standards workbook.
A46: Clause | B46: Clause name.
A47: Base severity | B47: Severity if the clause is missing or deviant. Editable for this contract (for example raise anti-bribery to Medium for a government counterparty). n/a for internal rules.
A48: Verdict | B48: Conforming, Partial, Deviant, Missing, Not supplied (the contract says the topic is governed by a document that was not supplied), or N/A (drop-down).
A49: Where | B49: Contract clause number and page where the clause was found.
A50: Severity | B50: Formula. Missing, Deviant or Not supplied = Base severity; Partial = one level lower (floor Low); Conforming or N/A = '-'.
A51: Note | B51: One line on what is present or absent. Details are in Findings.
A52: Sheet: Checks (one row per execution check)
A53: # | B53: Number of the check in the standards workbook.
A54: Check | B54: What is verified before a draft leaves Start2 and again before signature.
A55: Result | B55: Pass, Fail, N/A or Cannot verify (drop-down).
A56: Evidence | B56: What was seen, with page references.
A57: Sheet: Documents not supplied (one row per document)
A58: Document | B58: The document as the contract names it, with version or date if given.
A59: Referenced at | B59: Contract clause and page where it is named.
A60: Quote | B60: The contract text that names or incorporates it.
A61: Part of contract | B61: Yes when the contract says the document applies to or forms part of the contract. Those also appear in Findings as type Not supplied.
A62: Governs | B62: What the contract says or shows the document covers. Never a guess at its content.
A63: Effect on this review | B63: Which findings and coverage rows could not be completed without it.
A64: Action | B64: How to obtain it and what to check once it is in hand.
A65: Rules
A66: Counts | B66: Counts and the to-confirm line use the Findings sheet only. Coverage severity is a view and is not counted.
A67: Role | B67: The role is guessed when unclear and recorded on Summary. The only time the skill asks is when a name containing 'Start2' other than Start2 Asia appears: it flags the name and waits for confirmation.
A68: Not legal advice | B68: A screen against Start2 standards. Decisions follow the sign-off chain.

Sheet Summary
A1: Item | B1: Value | C1: Where
A2: Contract
A3: Contract
A4: Source file
A5: Status
A6: Contract type
A7: Whose paper
A8: Standards version
A9: Our side
A10: Our entity
A11: Our role
A12: Role basis
A13: Counterparty
A14: Result
A15: Critical | B15: =COUNTIF(Findings!$B$2:$B$300,"Critical")
A16: High | B16: =COUNTIF(Findings!$B$2:$B$300,"High")
A17: Medium | B17: =COUNTIF(Findings!$B$2:$B$300,"Medium")
A18: Low | B18: =COUNTIF(Findings!$B$2:$B$300,"Low")
A19: To confirm | B19: =IF(B11="","",IF(B11<>"Provider","Not assessed: the standards cover provider-side contracts only",(B15+B16)&" Critical and High findings to confirm"))
A20: Documents not supplied | B20: =COUNTA('Documents not supplied'!$B$2:$B$300)
A21: Review lead time | B21: =IF(B7="","",IF(B7="Start2 template, unmodified","3 business days","5 business days"))
A22: Sign-off chain | B22: 1. Director of People and Operations; 2. Regional Director of Innovation and Product Strategy; 3. CEO. Applies to every contract.
A23: Key facts

Sheet Findings
A1: # | B1: Severity | C1: Type | D1: Clause | E1: Where | F1: Quote | G1: Issue | H1: Action | I1: Suggested language | J1: Subjective

Sheet Coverage
A1: ID | B1: Clause | C1: Base severity | D1: Verdict | E1: Where | F1: Severity | G1: Note
A2: PARTIES | B2: Contracting entity & jurisdiction | C2: Critical | F2: =IF(D2="","",IF(OR(D2="Conforming",D2="N/A",C2="n/a"),"-",IF(D2="Partial",INDEX({"Low","Low","Medium","High"},MATCH(C2,{"Low","Medium","High","Critical"},0)),C2)))
A3: RECITALS | B3: Recitals | C3: Low | F3: =IF(D3="","",IF(OR(D3="Conforming",D3="N/A",C3="n/a"),"-",IF(D3="Partial",INDEX({"Low","Low","Medium","High"},MATCH(C3,{"Low","Medium","High","Critical"},0)),C3)))
A4: SCOPE | B4: Defined scope of service (Appendix) | C4: High | F4: =IF(D4="","",IF(OR(D4="Conforming",D4="N/A",C4="n/a"),"-",IF(D4="Partial",INDEX({"Low","Low","Medium","High"},MATCH(C4,{"Low","Medium","High","Critical"},0)),C4)))
A5: TERM | B5: Term | C5: High | F5: =IF(D5="","",IF(OR(D5="Conforming",D5="N/A",C5="n/a"),"-",IF(D5="Partial",INDEX({"Low","Low","Medium","High"},MATCH(C5,{"Low","Medium","High","Critical"},0)),C5)))
A6: FEE | B6: Fee, currency, payment trigger | C6: Critical | F6: =IF(D6="","",IF(OR(D6="Conforming",D6="N/A",C6="n/a"),"-",IF(D6="Partial",INDEX({"Low","Low","Medium","High"},MATCH(C6,{"Low","Medium","High","Critical"},0)),C6)))
A7: SETOFF | B7: No set-off | C7: High | F7: =IF(D7="","",IF(OR(D7="Conforming",D7="N/A",C7="n/a"),"-",IF(D7="Partial",INDEX({"Low","Low","Medium","High"},MATCH(C7,{"Low","Medium","High","Critical"},0)),C7)))
A8: LATEPAY | B8: Late payment: interest and right to suspend | C8: Medium | F8: =IF(D8="","",IF(OR(D8="Conforming",D8="N/A",C8="n/a"),"-",IF(D8="Partial",INDEX({"Low","Low","Medium","High"},MATCH(C8,{"Low","Medium","High","Critical"},0)),C8)))
A9: CONF | B9: Confidentiality | C9: High | F9: =IF(D9="","",IF(OR(D9="Conforming",D9="N/A",C9="n/a"),"-",IF(D9="Partial",INDEX({"Low","Low","Medium","High"},MATCH(C9,{"Low","Medium","High","Critical"},0)),C9)))
A10: ASSIGN | B10: Assignment restriction | C10: High | F10: =IF(D10="","",IF(OR(D10="Conforming",D10="N/A",C10="n/a"),"-",IF(D10="Partial",INDEX({"Low","Low","Medium","High"},MATCH(C10,{"Low","Medium","High","Critical"},0)),C10)))
A11: INDCON | B11: Independent contractor / no agency or partnership | C11: Medium | F11: =IF(D11="","",IF(OR(D11="Conforming",D11="N/A",C11="n/a"),"-",IF(D11="Partial",INDEX({"Low","Low","Medium","High"},MATCH(C11,{"Low","Medium","High","Critical"},0)),C11)))
A12: NOTICES | B12: Notices | C12: Low | F12: =IF(D12="","",IF(OR(D12="Conforming",D12="N/A",C12="n/a"),"-",IF(D12="Partial",INDEX({"Low","Low","Medium","High"},MATCH(C12,{"Low","Medium","High","Critical"},0)),C12)))
A13: AMEND | B13: Amendment | C13: Medium | F13: =IF(D13="","",IF(OR(D13="Conforming",D13="N/A",C13="n/a"),"-",IF(D13="Partial",INDEX({"Low","Low","Medium","High"},MATCH(C13,{"Low","Medium","High","Critical"},0)),C13)))
... A35: SEVERABILITY | B35: Severability clause | C35: Low | F35: =IF(D35="","",IF(OR(D35="Conforming",D35="N/A",C35="n/a"),"-",IF(D35="Partial",INDEX({"Low","Low","Medium","High"},MATCH(C35,{"Low","Medium","High","Critical"},0)),C35)))

Sheet Checks
A1: # | B1: Check | C1: Result | D1: Evidence
A2: 1 | B2: Every bracketed placeholder ([XXX], COMPANY DESCRIPTION, [Insert commencement event]) is filled. A signed agreement with a placeholder still in it is a live incident, not a defect, escalate immediately.
A3: 2 | B3: Clause numbering is sequential and matches any cross-references elsewhere in the document. Checked automatically by the assemble step for clauses built from the Clauses sheet.
A4: 3 | B4: Term dates in the recitals, the term clause, and Annex/Appendix all agree with each other.
A5: 4 | B5: Contracting entity name is identical everywhere it appears: cover page, signature block, bank details, and any Chinese or Korean-language mirror text.
A6: 5 | B6: Bilingual agreements: the two language versions say the same thing on fee, term dates, and liability cap at minimum. Have a fluent reviewer confirm, do not assume.
A7: 6 | B7: Signature block has the right number of lines for the actual signing parties, no blank line left for a party who will not sign.
A8: 7 | B8: Bank details in the payment clause match the named contracting entity, not a different Start2 entity.
A9: 8 | B9: No leftover tracked-change or redline artifacts in the body text.
A10: 9 | B10: Appendix or Schedule numbers referenced in the body match what is actually attached, no reference to a Schedule that doesn't exist.
A11: 10 | B11: Appendix content is specific to this deal, not another client's scope carried over from a previous draft.
A12: 11 | B12: Cross-references in the contract point to clauses and annexes that exist and are correctly numbered.
A13: 12 | B13: Currency, fee figures, governing law, and arbitration body match the actual contracting entity for this deal, not copy-paste residue from a different country's last draft.

Sheet Documents not supplied
A1: # | B1: Document | C1: Referenced at | D1: Quote | E1: Part of contract | F1: Governs | G1: Effect on this review | H1: Action
